audiostack/__init__.py
audiostack/content/__init__.py
audiostack/content/file.py
audiostack/content/recommend.py
audiostack/content/root_functions.py
audiostack/content/script.py
audiostack/delivery/__init__.py
audiostack/delivery/encoder.py
audiostack/delivery/video.py
audiostack/docs/__init__.py
audiostack/docs/docs.py
audiostack/helpers/__init__.py
audiostack/helpers/api_item.py
audiostack/helpers/api_list.py
audiostack/helpers/request_interface.py
audiostack/helpers/request_types.py
audiostack/helpers/response.py
audiostack/helpers/util.py
audiostack/orchestrator/__init__.py
audiostack/production/__init__.py
audiostack/production/mix.py
audiostack/production/sound.py
audiostack/production/suite.py
audiostack/speech/__init__.py
audiostack/speech/diction.py
audiostack/speech/predict.py
audiostack/speech/sts.py
audiostack/speech/tts.py
audiostack/speech/voice.py
audiostack-3.1.0.dist-info/LICENSE
audiostack-3.1.0.dist-info/METADATA
audiostack-3.1.0.dist-info/WHEEL
audiostack-3.1.0.dist-info/RECORD
