Metadata-Version: 2.1
Name: audiostack
Version: 3.1.0
Summary: Python SDK for Audiostack API
Home-page: https://github.com/aflorithmic/audiostack-python
Author: Aflorithmic
Author-email: support@audiostack.ai
Requires-Python: >=3.8.1,<4.0.0
Classifier: License :: OSI Approved :: MIT License
Classifier: Operating System :: OS Independent
Classifier: Programming Language :: Python :: 3
Classifier: Programming Language :: Python :: 3.9
Classifier: Programming Language :: Python :: 3.10
Classifier: Programming Language :: Python :: 3.11
Classifier: Programming Language :: Python :: 3.12
Requires-Dist: requests (>=2.31.0,<3.0.0)
Project-URL: Changelog, https://github.com/aflorithmic/audiostack-python/blob/main/CHANGELOG.md
Project-URL: Repository, https://github.com/aflorithmic/audiostack-python
